main.py
snsr-0.1.5.dist-info/METADATA
snsr-0.1.5.dist-info/WHEEL
snsr-0.1.5.dist-info/entry_points.txt
snsr-0.1.5.dist-info/top_level.txt
snsr-0.1.5.dist-info/RECORD
