Metadata-Version: 2.4
Name: snsr
Version: 0.1.5
Summary: A simple random movement screensaver.
Author: nichsedge
License: MIT
Project-URL: Homepage, https://github.com/nichsedge/snsr
Requires-Python: >=3.7
Requires-Dist: pyautogui>=0.9.54
